crimson/data_class/__init__.py
crimson/data_class/data_class_list.py
crimson/data_class/pandas.py
crimson_data_class-0.1.4.dist-info/LICENSE
crimson_data_class-0.1.4.dist-info/METADATA
crimson_data_class-0.1.4.dist-info/WHEEL
crimson_data_class-0.1.4.dist-info/top_level.txt
crimson_data_class-0.1.4.dist-info/RECORD
