Metadata-Version: 2.1
Name: crimson-data-class
Version: 0.1.4
Summary: From source code, extract useful information.
Author-email: Sisung Kim <sisung.kim1@gmail.com>
Project-URL: Homepage, https://github.com/crimson206/data-class
Project-URL: Bug Tracker, https://github.com/crimson206/data-class/issues
Classifier: Programming Language :: Python :: 3
Classifier: Intended Audience :: Developers
Classifier: Topic :: Software Development :: Build Tools
Classifier: License :: OSI Approved :: MIT License
Classifier: Operating System :: OS Independent
Requires-Python: >=3.9
License-File: LICENSE
Requires-Dist: pydantic
